pipgh/__init__.py
pipgh/__main__.py
pipgh/pipgh.py
pipgh/terminalsize.py
pipgh/tools.py
pipgh-0.0.6.dist-info/DESCRIPTION.rst
pipgh-0.0.6.dist-info/METADATA
pipgh-0.0.6.dist-info/RECORD
pipgh-0.0.6.dist-info/WHEEL
pipgh-0.0.6.dist-info/entry_points.txt
pipgh-0.0.6.dist-info/metadata.json
pipgh-0.0.6.dist-info/pbr.json
pipgh-0.0.6.dist-info/top_level.txt
