Metadata-Version: 2.0
Name: pipgh
Version: 0.0.6
Summary: A tool to install python packages from Github.
Home-page: https://github.com/ffunenga/pipgh
Author: Filipe Funenga
Author-email: fmafunenga@gmail.com
License: MIT
Platform: UNKNOWN
